csbluegem/__init__.py
csbluegem/client.py
csbluegem/errors.py
csbluegem/http.py
csbluegem/meta.py
csbluegem/types.py
csbluegem/utils.py
csbluegem.py-0.14.0.dist-info/LICENSE
csbluegem.py-0.14.0.dist-info/METADATA
csbluegem.py-0.14.0.dist-info/WHEEL
csbluegem.py-0.14.0.dist-info/top_level.txt
csbluegem.py-0.14.0.dist-info/RECORD
