Metadata-Version: 2.1
Name: csbluegem.py
Version: 0.14.0
Summary: An async wrapper for the CSBlueGem api.
Author-email: fretgfr <fretgfr@sudomail.com>
License: Copyright 2024-present fretgfr
Project-URL: Homepage, https://github.com/fretgfr/csbluegem.py/
Project-URL: Documentation, https://csbluegempy.readthedocs.io/en/latest/
Project-URL: Issues, https://github.com/fretgfr/csbluegem.py/issues
Keywords: csbluegem,counter strike,api wrapper
Classifier: License :: OSI Approved :: MIT License
Classifier: Programming Language :: Python
Classifier: Programming Language :: Python :: 3
Requires-Python: >=3.8
License-File: LICENSE
Requires-Dist: aiohttp<4,>=3.7.4
Provides-Extra: dev
Requires-Dist: black; extra == "dev"
Requires-Dist: isort; extra == "dev"
Requires-Dist: typing_extensions; extra == "dev"
Provides-Extra: docs
Requires-Dist: sphinx; extra == "docs"
Requires-Dist: sphinx-rtd-theme; extra == "docs"
